asciirend/__init__.py
asciirend/wasm.wasm
asciirend-0.3.0.dist-info/METADATA
asciirend-0.3.0.dist-info/WHEEL
asciirend-0.3.0.dist-info/top_level.txt
asciirend-0.3.0.dist-info/RECORD
