Metadata-Version: 2.1
Name: asciirend
Version: 0.3.0
Summary: ascii rendering engine
Home-page: https://github.com/h33p/asciirend
Author: Aurimas Blažulionis
Author-email: 0x60@pm.me
Classifier: Development Status :: 3 - Alpha
Classifier: Intended Audience :: Developers
Classifier: License :: OSI Approved :: MIT License
Classifier: Programming Language :: Python :: 3
Requires-Dist: wasmtime
